alliance_platform/codegen/__init__.py
alliance_platform/codegen/apps.py
alliance_platform/codegen/post_processors/__init__.py
alliance_platform/codegen/post_processors/js.py
alliance_platform/codegen/printer.py
alliance_platform/codegen/py.typed
alliance_platform/codegen/registry.py
alliance_platform/codegen/settings.py
alliance_platform/codegen/typescript.py
alliance_platform_codegen-0.0.9.dist-info/METADATA
alliance_platform_codegen-0.0.9.dist-info/WHEEL
alliance_platform_codegen-0.0.9.dist-info/entry_points.txt
alliance_platform_codegen-0.0.9.dist-info/RECORD
