Metadata-Version: 2.1
Name: alliance-platform-codegen
Version: 0.0.9
Summary: Alliance Platform Codegen
Author-Email: Alliance Software <support@alliancesoftware.com.au>
License: BSD-2-Clause
Requires-Python: >=3.11
Requires-Dist: alliance-platform-core
Requires-Dist: Django>=4.2.11
Requires-Dist: django-allianceutils>=4.0
